azure/media/analyticsedge/__init__.py
azure/media/analyticsedge/_version.py
azure/media/analyticsedge/_generated/__init__.py
azure/media/analyticsedge/_generated/_version.py
azure/media/analyticsedge/_generated/models/__init__.py
azure/media/analyticsedge/_generated/models/_direct_methodsfor_live_video_analyticson_io_tedge_enums.py
azure/media/analyticsedge/_generated/models/_models.py
azure/media/analyticsedge/_generated/models/_models_py3.py
azure_media_analytics_edge-1.0.0b2.dist-info/METADATA
azure_media_analytics_edge-1.0.0b2.dist-info/WHEEL
azure_media_analytics_edge-1.0.0b2.dist-info/top_level.txt
azure_media_analytics_edge-1.0.0b2.dist-info/RECORD
