Metadata-Version: 2.1
Name: azure-media-analytics-edge
Version: 1.0.0b2
Summary: Microsoft Azure Media Live Video Analytics Edge SDK Library for Python
Home-page: https://github.com/Azure/azure-sdk-for-python/tree/main/sdk/media/azure-media-analytics-edge
Author: Microsoft Corporation
Author-email: azpysdkhelp@microsoft.com
License: MIT License
Platform: UNKNOWN
Classifier: Development Status :: 7 - Inactive
Classifier: Programming Language :: Python
Classifier: Programming Language :: Python :: 2
Classifier: Programming Language :: Python :: 2.7
Classifier: Programming Language :: Python :: 3
Classifier: Programming Language :: Python :: 3.5
Classifier: Programming Language :: Python :: 3.6
Classifier: Programming Language :: Python :: 3.7
Classifier: Programming Language :: Python :: 3.8
Classifier: Programming Language :: Python :: 3.9
Classifier: License :: OSI Approved :: MIT License
Requires-Dist: msrest (>=0.6.21)
Requires-Dist: azure-media-nspkg ; python_version<'3.0'
Requires-Dist: enum34 (>=1.0.4) ; python_version<'3.4'
Requires-Dist: typing ; python_version<'3.5'
